YiriAir/__init__.py
YiriAir/bot.py
YiriAir/codec.py
YiriAir/driver.py
YiriAir-0.0.4.dist-info/LICENSE
YiriAir-0.0.4.dist-info/METADATA
YiriAir-0.0.4.dist-info/WHEEL
YiriAir-0.0.4.dist-info/top_level.txt
YiriAir-0.0.4.dist-info/RECORD
