Metadata-Version: 2.1
Name: YiriAir
Version: 0.0.4
Summary: 基于安卓模拟器和 UI 控件搜索的 QQ 消息自动收发框架。
Home-page: https://github.com/Wybxc/YiriAir
Author: wybxc
Author-email: wybxc@qq.com
License: AGPL-3.0 License
Platform: all
Classifier: Development Status :: 4 - Beta
Classifier: Operating System :: OS Independent
Classifier: Intended Audience :: Developers
Classifier: License :: OSI Approved :: GNU Affero General Public License v3
Classifier: Programming Language :: Python :: 3
Classifier: Programming Language :: Python :: 3.4
Classifier: Programming Language :: Python :: 3.5
Classifier: Programming Language :: Python :: 3.6
Classifier: Programming Language :: Python :: 3.7
Classifier: Programming Language :: Python :: 3.8
Classifier: Topic :: Software Development :: Libraries
Requires-Dist: airtest (>=1.1.1)
Requires-Dist: pocoui (>=1.0.78)
Requires-Dist: emoji
